{
  "skill": "monthly-marketing-digest",
  "title": "Monthly Funnel & Revenue",
  "updated": "2026-06-03",
  "fiscal_year_start_month": 10,
  "seasonality": {
    "peak_close": ["May", "Jun"],
    "peak_leadgen": ["Jan", "Feb"],
    "low": ["Jul", "Aug"],
    "note": "Close/fiscal year = Oct 1–Sep 30 (pipeline + cumulative win rate measured against it). District buying follows the school year: deals peak spring–summer (Apr–Aug, buying for next school year) — which is why revenue concentrates May–Jul, offset from inquirED's Sep 30 close. Lead-gen builds fall–winter; Jan–Feb peak; summer low."
  },
  "notes": "Revenue/funnel/web backfilled from HubSpot + GA4 (Jun 2025–May 2026). Backfill is not test-deal-excluded; the current month (May 2026) uses the clean, test+RFP-excluded figures from the digest. SEO baseline starts May 2026.",
  "months": [
    {"period": "2025-06", "label": "Jun 2025", "funnel": {"hih": 82, "mql": 127, "sql": 38, "opp": 44}, "revenue": {"district_won": 320014.36, "school_won": 20806.51, "total_won": 340820.87, "wins": 26}, "web": {"sessions": 9508, "users": 7404, "views": 11179}, "seo": {"tracked": null, "top10": null, "avg_position": null}},
    {"period": "2025-07", "label": "Jul 2025", "funnel": {"hih": 49, "mql": 137, "sql": 52, "opp": 53}, "revenue": {"district_won": 467121.79, "school_won": 53244, "total_won": 520365.79, "wins": 34}, "web": {"sessions": 7962, "users": 5941, "views": 9068}, "seo": {"tracked": null, "top10": null, "avg_position": null}},
    {"period": "2025-08", "label": "Aug 2025", "funnel": {"hih": 13, "mql": 195, "sql": 101, "opp": 98}, "revenue": {"district_won": 35735.84, "school_won": 20954, "total_won": 56689.84, "wins": 23}, "web": {"sessions": 11372, "users": 8455, "views": 13315}, "seo": {"tracked": null, "top10": null, "avg_position": null}},
    {"period": "2025-09", "label": "Sep 2025", "funnel": {"hih": 27, "mql": 305, "sql": 120, "opp": 120}, "revenue": {"district_won": 20287.41, "school_won": 2498.36, "total_won": 22785.77, "wins": 12}, "web": {"sessions": 26003, "users": 14932, "views": 37996}, "seo": {"tracked": null, "top10": null, "avg_position": null}},
    {"period": "2025-10", "label": "Oct 2025", "funnel": {"hih": 33, "mql": 682, "sql": 497, "opp": 499}, "revenue": {"district_won": 4731, "school_won": 0, "total_won": 4731, "wins": 8}, "web": {"sessions": 35976, "users": 22925, "views": 55655}, "seo": {"tracked": null, "top10": null, "avg_position": null}},
    {"period": "2025-11", "label": "Nov 2025", "funnel": {"hih": 86, "mql": 144, "sql": 43, "opp": 42}, "revenue": {"district_won": 5184.3, "school_won": 0, "total_won": 5184.3, "wins": 5}, "web": {"sessions": 21037, "users": 12087, "views": 28515}, "seo": {"tracked": null, "top10": null, "avg_position": null}},
    {"period": "2025-12", "label": "Dec 2025", "funnel": {"hih": 36, "mql": 136, "sql": 70, "opp": 71}, "revenue": {"district_won": 11250, "school_won": 0, "total_won": 11250, "wins": 5}, "web": {"sessions": 14977, "users": 7396, "views": 21778}, "seo": {"tracked": null, "top10": null, "avg_position": null}},
    {"period": "2026-01", "label": "Jan 2026", "funnel": {"hih": 75, "mql": 145, "sql": 37, "opp": 30}, "revenue": {"district_won": 15241.6, "school_won": 0, "total_won": 15241.6, "wins": 9}, "web": {"sessions": 19498, "users": 9910, "views": 27991}, "seo": {"tracked": null, "top10": null, "avg_position": null}},
    {"period": "2026-02", "label": "Feb 2026", "funnel": {"hih": 89, "mql": 313, "sql": 69, "opp": 69}, "revenue": {"district_won": 7805, "school_won": 250, "total_won": 8055, "wins": 8}, "web": {"sessions": 21773, "users": 12063, "views": 34254}, "seo": {"tracked": null, "top10": null, "avg_position": null}},
    {"period": "2026-03", "label": "Mar 2026", "funnel": {"hih": 70, "mql": 437, "sql": 68, "opp": 65}, "revenue": {"district_won": 4000, "school_won": 0, "total_won": 4000, "wins": 4}, "web": {"sessions": 23590, "users": 12652, "views": 33258}, "seo": {"tracked": null, "top10": null, "avg_position": null}},
    {"period": "2026-04", "label": "Apr 2026", "funnel": {"hih": 73, "mql": 164, "sql": 76, "opp": 78}, "revenue": {"district_won": 11249, "school_won": 1900, "total_won": 13149, "wins": 6}, "web": {"sessions": 17696, "users": 9215, "views": 25746}, "seo": {"tracked": null, "top10": null, "avg_position": null}},
    {"period": "2026-05", "label": "May 2026", "funnel": {"hih": 99, "mql": 142, "sql": 67, "opp": 66}, "revenue": {"district_won": 83853.38, "school_won": 21363, "total_won": 105216.38, "nb_won": 103216.38, "existing_won": 2000, "wins": 11, "win_rate_count_pct": 21.2, "win_rate_dollar_pct": 15.3, "by_segment": {"single_small": {"won": 41759, "lost": 133927}, "medium": {"won": 0, "lost": 225518}, "large": {"won": 0, "lost": 71000}, "enterprise": {"won": 63457, "lost": 150000}}}, "web": {"sessions": 39181, "users": 12663, "views": 32590, "yoy": {"sessions": 14781, "users": 9861, "views": 16126}}, "seo": {"tracked": 152, "top10": 33, "avg_position": 4.4, "ranked": 38}}
  ]
}
